jmspack/NLTSA.py
jmspack/__init__.py
jmspack/frequentist_statistics.py
jmspack/imputation_utils.py
jmspack/internal_utils.py
jmspack/ml_utils.py
jmspack/networks.py
jmspack/utils.py
jmspack-0.1.2.dist-info/LICENSE
jmspack-0.1.2.dist-info/METADATA
jmspack-0.1.2.dist-info/WHEEL
jmspack-0.1.2.dist-info/top_level.txt
jmspack-0.1.2.dist-info/RECORD
