Metadata-Version: 2.1
Name: jmspack
Version: 0.1.2
Summary: James Data Science package
Home-page: https://github.com/jameshtwose/jmspack
Author: James Twose
Author-email: contact@jamestwose.com
License: BSD (3-clause)
License-File: LICENSE
Requires-Dist: seaborn (>=0.11.0)
Requires-Dist: statsmodels (>=0.12.0)
Requires-Dist: scikit-learn (>=0.23.0)
Requires-Dist: requests (>=2.24.0)
